augmentdata/__init__.py
augmentdata/data_augment.py
augmentdata/test_nn.py
augmentdata/tests/__init__.py
augmentdata/tests/test_augmented.py
augmentdata-0.0.12.dist-info/LICENSE.rst
augmentdata-0.0.12.dist-info/METADATA
augmentdata-0.0.12.dist-info/WHEEL
augmentdata-0.0.12.dist-info/top_level.txt
augmentdata-0.0.12.dist-info/RECORD
