Metadata-Version: 2.1
Name: augmentdata
Version: 0.0.12
Summary: Generic python library to perform augmentation of data
Home-page: UNKNOWN
Author: Sameer Brahim Belhaouari, Ashhadul Islam
Author-email: samir.brahim@gmail.com, ashhadulislam@gmail.com
License: MIT
Keywords: Binary Classification,Data Augmentation,Imabalnced Data
Platform: UNKNOWN
Requires-Dist: numpy
